[{"line":1,"elements":[{"start_timestamp":"2024-03-13T09:15:47.580Z","before":[{"result":{"duration":4798788000,"status":"passed"},"match":{"location":"cucumber.StepDefinitions.SharedSteps.setup()"}}],"line":3,"name":"User logs in with valid credentials","description":"","id":"login-functionality;user-logs-in-with-valid-credentials","after":[{"result":{"duration":108946300,"status":"passed"},"match":{"location":"cucumber.StepDefinitions.SharedSteps.tearDown()"}}],"type":"scenario","keyword":"Scenario","steps":[{"result":{"duration":522908700,"status":"passed"},"line":4,"name":"User is on the login page","match":{"location":"cucumber.StepDefinitions.LoginStepDefinitions.user_is_on_the_login_page()"},"keyword":"Given "},{"result":{"duration":113947600,"status":"passed"},"line":5,"name":"User enters valid username and password","match":{"location":"cucumber.StepDefinitions.LoginStepDefinitions.user_enters_valid_username_and_password()"},"keyword":"When "},{"result":{"duration":1004367100,"status":"passed"},"line":6,"name":"User should be logged in successfully","match":{"location":"cucumber.StepDefinitions.LoginStepDefinitions.user_should_be_logged_in_successfully()"},"keyword":"Then "}]}],"name":"Login Functionality","description":"","id":"login-functionality","keyword":"Feature","uri":"file:src/test/resources/Features/login.feature","tags":[]},{"line":1,"elements":[{"start_timestamp":"2024-03-13T09:15:54.150Z","before":[{"result":{"duration":3107106200,"status":"passed"},"match":{"location":"cucumber.StepDefinitions.SharedSteps.setup()"}}],"line":10,"name":"User searches for a product","description":"","id":"search-product-functionality;user-searches-for-a-product;;2","after":[{"result":{"duration":110825000,"status":"passed"},"match":{"location":"cucumber.StepDefinitions.SharedSteps.tearDown()"}}],"type":"scenario","keyword":"Scenario","steps":[{"result":{"duration":1387507500,"status":"passed"},"line":4,"name":"User is logged in","match":{"location":"cucumber.StepDefinitions.SearchProductStepDefinitions.user_is_logged_in()"},"keyword":"Given "},{"result":{"duration":892168200,"status":"passed"},"line":5,"name":"User searches for a product \"Computer\"","match":{"arguments":[{"val":"\"Computer\"","offset":28}],"location":"cucumber.StepDefinitions.SearchProductStepDefinitions.user_searches_for_a_product(java.lang.String)"},"keyword":"When "},{"result":{"duration":32503400,"status":"passed"},"line":6,"name":"Search results should be displayed \"Computer Title\"","match":{"arguments":[{"val":"\"Computer Title\"","offset":35}],"location":"cucumber.StepDefinitions.SearchProductStepDefinitions.search_results_should_be_displayed(java.lang.String)"},"keyword":"Then "}]},{"start_timestamp":"2024-03-13T09:15:59.684Z","before":[{"result":{"duration":3423980500,"status":"passed"},"match":{"location":"cucumber.StepDefinitions.SharedSteps.setup()"}}],"line":11,"name":"User searches for a product","description":"","id":"search-product-functionality;user-searches-for-a-product;;3","after":[{"result":{"duration":86086000,"status":"passed"},"match":{"location":"cucumber.StepDefinitions.SharedSteps.tearDown()"}}],"type":"scenario","keyword":"Scenario","steps":[{"result":{"duration":1419952200,"status":"passed"},"line":4,"name":"User is logged in","match":{"location":"cucumber.StepDefinitions.SearchProductStepDefinitions.user_is_logged_in()"},"keyword":"Given "},{"result":{"duration":874573900,"status":"passed"},"line":5,"name":"User searches for a product \"Health Book\"","match":{"arguments":[{"val":"\"Health Book\"","offset":28}],"location":"cucumber.StepDefinitions.SearchProductStepDefinitions.user_searches_for_a_product(java.lang.String)"},"keyword":"When "},{"result":{"duration":30154300,"status":"passed"},"line":6,"name":"Search results should be displayed \"Book Title\"","match":{"arguments":[{"val":"\"Book Title\"","offset":35}],"location":"cucumber.StepDefinitions.SearchProductStepDefinitions.search_results_should_be_displayed(java.lang.String)"},"keyword":"Then "}]},{"start_timestamp":"2024-03-13T09:16:05.521Z","before":[{"result":{"duration":3195098100,"status":"passed"},"match":{"location":"cucumber.StepDefinitions.SharedSteps.setup()"}}],"line":12,"name":"User searches for a product","description":"","id":"search-product-functionality;user-searches-for-a-product;;4","after":[{"result":{"duration":105885000,"status":"passed"},"match":{"location":"cucumber.StepDefinitions.SharedSteps.tearDown()"}}],"type":"scenario","keyword":"Scenario","steps":[{"result":{"duration":1335587400,"status":"passed"},"line":4,"name":"User is logged in","match":{"location":"cucumber.StepDefinitions.SearchProductStepDefinitions.user_is_logged_in()"},"keyword":"Given "},{"result":{"duration":828901600,"status":"passed"},"line":5,"name":"User searches for a product \"Blue Jeans\"","match":{"arguments":[{"val":"\"Blue Jeans\"","offset":28}],"location":"cucumber.StepDefinitions.SearchProductStepDefinitions.user_searches_for_a_product(java.lang.String)"},"keyword":"When "},{"result":{"duration":27158000,"status":"passed"},"line":6,"name":"Search results should be displayed \"Jeans Title\"","match":{"arguments":[{"val":"\"Jeans Title\"","offset":35}],"location":"cucumber.StepDefinitions.SearchProductStepDefinitions.search_results_should_be_displayed(java.lang.String)"},"keyword":"Then "}]}],"name":"Search Product Functionality","description":"","id":"search-product-functionality","keyword":"Feature","uri":"file:src/test/resources/Features/search.feature","tags":[]}]